retrival25/__init__.py
retrival25/atire_bm25.py
retrival25/base.py
retrival25/bm25L.py
retrival25/bm25_adpt.py
retrival25/bm25_plus.py
retrival25/rank.py
retrival25/robertson.py
tests/__init__.py
retrival25-1.0.0.dist-info/LICENSE
retrival25-1.0.0.dist-info/METADATA
retrival25-1.0.0.dist-info/WHEEL
retrival25-1.0.0.dist-info/top_level.txt
retrival25-1.0.0.dist-info/RECORD
