Metadata-Version: 2.1
Name: retrival25
Version: 1.0.0
Summary: One place stop for BM25 and it's variants
Home-page: https://github.com/akashchaudhari98/retrival25
Author: Akash Chaudhari
Author-email: akashchaudhari726@gmail.com
Classifier: Programming Language :: Python :: 3
Classifier: License :: OSI Approved :: MIT License
Classifier: Operating System :: OS Independent
Requires-Python: >=3.6
License-File: LICENSE
Requires-Dist: numpy
Requires-Dist: pandas
Requires-Dist: scipy
Requires-Dist: tok
